fakeuser/__init__.py
fakeuser/cache.py
fakeuser/cli.py
fakeuser/core.py
fakeuser/downloader.py
fakeuser/timezone_mappings.py
fakeuser-1.0.0.dist-info/licenses/LICENSE
fakeuser-1.0.0.dist-info/METADATA
fakeuser-1.0.0.dist-info/WHEEL
fakeuser-1.0.0.dist-info/entry_points.txt
fakeuser-1.0.0.dist-info/top_level.txt
fakeuser-1.0.0.dist-info/RECORD
