Metadata-Version: 2.4
Name: fakeuser
Version: 1.0.0
Summary: Generate realistic user data with accurate geographic information
Home-page: https://github.com/hoolymama/fakeuser
Author: Julian Man
Author-email: julian.mann@gmail.com
Project-URL: Bug Reports, https://github.com/hoolymama/fakeuser/issues
Project-URL: Source, https://github.com/hoolymama/fakeuser
Project-URL: Documentation, https://github.com/hoolymama/fakeuser#readme
Keywords: fake users location testing geonames randomuser geographic data
Classifier: Development Status :: 4 - Beta
Classifier: Intended Audience :: Developers
Classifier: Topic :: Software Development :: Testing
Classifier: License :: OSI Approved :: MIT License
Classifier: Programming Language :: Python :: 3
Classifier: Programming Language :: Python :: 3.8
Classifier: Programming Language :: Python :: 3.9
Classifier: Programming Language :: Python :: 3.10
Classifier: Programming Language :: Python :: 3.11
Requires-Python: >=3.8
License-File: LICENSE
Requires-Dist: requests>=2.25.0
Dynamic: author
Dynamic: author-email
Dynamic: classifier
Dynamic: description
Dynamic: description-content-type
Dynamic: home-page
Dynamic: keywords
Dynamic: license-file
Dynamic: project-url
Dynamic: requires-dist
Dynamic: requires-python
Dynamic: summary
